cordada/__init__.py
cordada/pe_sunat/__init__.py
cordada/pe_sunat/py.typed
cordada/pe_sunat/ruc/__init__.py
cordada/pe_sunat/ruc/constants.py
cordada/pe_sunat/ruc/entities.py
cordada/pe_sunat/tests/__init__.py
cordada/pe_sunat/tests/test_ruc_entities.py
pe_sunat-1.6.0.dist-info/LICENSE
pe_sunat-1.6.0.dist-info/METADATA
pe_sunat-1.6.0.dist-info/WHEEL
pe_sunat-1.6.0.dist-info/top_level.txt
pe_sunat-1.6.0.dist-info/RECORD
