Metadata-Version: 2.1
Name: pe-sunat
Version: 1.6.0
Summary: Python library for Superintendencia Nacional de Aduanas y de Administración Tributaria (SUNAT) of Peru.
Author-email: Cordada SpA <no-reply@cordada.com>
License: MIT
Project-URL: Homepage, https://github.com/cordada/lib-pe-sunat-python/
Project-URL: Changelog, https://github.com/cordada/lib-pe-sunat-python/blob/develop/CHANGELOG.md
Classifier: Development Status :: 3 - Alpha
Classifier: Intended Audience :: Developers
Classifier: License :: OSI Approved :: MIT License
Classifier: Natural Language :: English
Classifier: Operating System :: OS Independent
Classifier: Programming Language :: Python :: 3
Classifier: Programming Language :: Python :: 3.9
Classifier: Programming Language :: Python :: 3.10
Requires-Python: >=3.8
License-File: LICENSE
